kokoro_manim_voiceover-0.1.3.dist-info/licenses/LICENSE
kokoro_mv/__init__.py
kokoro_mv/koko.py
kokoro_mv/setup.py
kokoro_manim_voiceover-0.1.3.dist-info/METADATA
kokoro_manim_voiceover-0.1.3.dist-info/WHEEL
kokoro_manim_voiceover-0.1.3.dist-info/entry_points.txt
kokoro_manim_voiceover-0.1.3.dist-info/top_level.txt
kokoro_manim_voiceover-0.1.3.dist-info/RECORD
