Metadata-Version: 2.4
Name: kokoro-manim-voiceover
Version: 0.1.3
Summary: Professional library for generating high-quality voiceovers in Manim animations using Kokoro-82M model
Author-email: Nadeem Akhtar Khan <nadeemak755@gmail.com>
Maintainer-email: Nadeem Akhtar Khan <nadeemak755@gmail.com>
License-Expression: MIT
Project-URL: Homepage, https://github.com/nkayzai/kokoro-manim-voiceover
Project-URL: Repository, https://github.com/nkayzai/kokoro-manim-voiceover
Project-URL: Documentation, https://github.com/nkayzai/kokoro-manim-voiceover#readme
Project-URL: Bug Tracker, https://github.com/nkayzai/kokoro-manim-voiceover/issues
Keywords: manim,voiceover,text-to-speech,kokoro,animation,tts,ai-voice
Classifier: Development Status :: 4 - Beta
Classifier: Intended Audience :: Developers
Classifier: Operating System :: OS Independent
Classifier: Programming Language :: Python :: 3
Classifier: Programming Language :: Python :: 3.11
Classifier: Programming Language :: Python :: 3.12
Classifier: Programming Language :: Python :: 3.13
Classifier: Topic :: Multimedia :: Graphics
Classifier: Topic :: Multimedia :: Sound/Audio :: Speech
Classifier: Topic :: Scientific/Engineering :: Artificial Intelligence
Classifier: Topic :: Software Development :: Libraries :: Python Modules
Requires-Python: >=3.11
License-File: LICENSE
Requires-Dist: kokoro-onnx>=0.3.6
Requires-Dist: manim>=0.19.0
Requires-Dist: manim-voiceover>=0.3.7
Requires-Dist: soundfile>=0.13.0
Requires-Dist: numpy>=1.21.0
Requires-Dist: scipy>=1.7.0
Requires-Dist: setuptools>=75.8.0
Requires-Dist: tqdm>=4.64.0
Provides-Extra: dev
Requires-Dist: pytest>=7.0.0; extra == "dev"
Requires-Dist: pytest-cov>=4.0.0; extra == "dev"
Requires-Dist: black>=23.0.0; extra == "dev"
Requires-Dist: isort>=5.12.0; extra == "dev"
Requires-Dist: flake8>=6.0.0; extra == "dev"
Requires-Dist: mypy>=1.0.0; extra == "dev"
Dynamic: license-file
